rptminigameshub/__init__.py
rpt_minigames_hub-0.0.0.dist-info/LICENSE
rpt_minigames_hub-0.0.0.dist-info/METADATA
rpt_minigames_hub-0.0.0.dist-info/WHEEL
rpt_minigames_hub-0.0.0.dist-info/top_level.txt
rpt_minigames_hub-0.0.0.dist-info/RECORD
